{
  "_metadata": {
    "script": "code/build_era_conditional_shocks_walkforward.py",
    "method": "no-look-ahead expanding within-era q90 after warmup; prior-era q99 tail fallback during warmup (catches obvious shocks like COVID; no prior-era-q90 bias)",
    "panel_path": "/home/runner/work/bitcoin-shock/bitcoin-shock/data/panel_with_shocks.parquet",
    "quantile": 0.9,
    "warmup_obs": 60,
    "tail_quantile_during_warmup": 0.99,
    "eras": [
      {
        "name": "pre_covid",
        "start": "2014-01-02",
        "end": "2020-02-29"
      },
      {
        "name": "post_covid_pre_etf",
        "start": "2020-03-01",
        "end": "2024-01-09"
      },
      {
        "name": "post_etf",
        "start": "2024-01-10",
        "end": "2099-12-31"
      }
    ],
    "generated_at": "2026-07-11T08:08:35.993415Z",
    "seed": 42
  },
  "shock_incidence": {
    "oil_shock": {
      "raw_col": "wti",
      "measure_kind": "abs_log_diff",
      "walkforward_overall_incidence": 0.09873745548721269,
      "n_classified_total": 3089,
      "n_warmup_dropped_total": 63,
      "by_era": {
        "pre_covid": {
          "n_total": 1550,
          "n_classified": 1489,
          "n_warmup_dropped": 61,
          "walkforward_incidence": 0.10745466756212223,
          "end_of_era_cutoff": 0.03656973446016156
        },
        "post_covid_pre_etf": {
          "n_total": 972,
          "n_classified": 970,
          "n_warmup_dropped": 2,
          "walkforward_incidence": 0.05670103092783505,
          "end_of_era_cutoff": 0.04489349343748502
        },
        "post_etf": {
          "n_total": 630,
          "n_classified": 630,
          "n_warmup_dropped": 0,
          "walkforward_incidence": 0.14285714285714285,
          "end_of_era_cutoff": 0.03401242879972745
        }
      }
    },
    "dollar_shock": {
      "raw_col": "usd_broad",
      "measure_kind": "abs_diff",
      "walkforward_overall_incidence": 0.10287932707861533,
      "n_classified_total": 3091,
      "n_warmup_dropped_total": 61,
      "by_era": {
        "pre_covid": {
          "n_total": 1550,
          "n_classified": 1489,
          "n_warmup_dropped": 61,
          "walkforward_incidence": 0.10946944257891202,
          "end_of_era_cutoff": 0.5211599999999988
        },
        "post_covid_pre_etf": {
          "n_total": 972,
          "n_classified": 972,
          "n_warmup_dropped": 0,
          "walkforward_incidence": 0.08539094650205761,
          "end_of_era_cutoff": 0.6873999999999967
        },
        "post_etf": {
          "n_total": 630,
          "n_classified": 630,
          "n_warmup_dropped": 0,
          "walkforward_incidence": 0.11428571428571428,
          "end_of_era_cutoff": 0.5879600000000046
        }
      }
    },
    "rate_shock": {
      "raw_col": "y10_fred",
      "measure_kind": "abs_diff",
      "walkforward_overall_incidence": 0.09576188935619541,
      "n_classified_total": 3091,
      "n_warmup_dropped_total": 61,
      "by_era": {
        "pre_covid": {
          "n_total": 1550,
          "n_classified": 1489,
          "n_warmup_dropped": 61,
          "walkforward_incidence": 0.08327736736064473,
          "end_of_era_cutoff": 0.06999999999999984
        },
        "post_covid_pre_etf": {
          "n_total": 972,
          "n_classified": 972,
          "n_warmup_dropped": 0,
          "walkforward_incidence": 0.13580246913580246,
          "end_of_era_cutoff": 0.10000000000000009
        },
        "post_etf": {
          "n_total": 630,
          "n_classified": 630,
          "n_warmup_dropped": 0,
          "walkforward_incidence": 0.06349206349206349,
          "end_of_era_cutoff": 0.08000000000000007
        }
      }
    },
    "banking_shock": {
      "raw_col": "stlfsi",
      "measure_kind": "level",
      "walkforward_overall_incidence": 0.11772315653298836,
      "n_classified_total": 3092,
      "n_warmup_dropped_total": 60,
      "by_era": {
        "pre_covid": {
          "n_total": 1550,
          "n_classified": 1490,
          "n_warmup_dropped": 60,
          "walkforward_incidence": 0.14228187919463087,
          "end_of_era_cutoff": 0.2757000000000005
        },
        "post_covid_pre_etf": {
          "n_total": 972,
          "n_classified": 972,
          "n_warmup_dropped": 0,
          "walkforward_incidence": 0.06275720164609054,
          "end_of_era_cutoff": 0.4198
        },
        "post_etf": {
          "n_total": 630,
          "n_classified": 630,
          "n_warmup_dropped": 0,
          "walkforward_incidence": 0.14444444444444443,
          "end_of_era_cutoff": -0.3153
        }
      }
    },
    "gprd_threat_shock": {
      "raw_col": "gprd_threat",
      "measure_kind": "level",
      "walkforward_overall_incidence": 0.15265200517464425,
      "n_classified_total": 3092,
      "n_warmup_dropped_total": 60,
      "by_era": {
        "pre_covid": {
          "n_total": 1550,
          "n_classified": 1490,
          "n_warmup_dropped": 60,
          "walkforward_incidence": 0.12818791946308725,
          "end_of_era_cutoff": 196.5566589355469
        },
        "post_covid_pre_etf": {
          "n_total": 972,
          "n_classified": 972,
          "n_warmup_dropped": 0,
          "walkforward_incidence": 0.15637860082304528,
          "end_of_era_cutoff": 247.38201904296875
        },
        "post_etf": {
          "n_total": 630,
          "n_classified": 630,
          "n_warmup_dropped": 0,
          "walkforward_incidence": 0.20476190476190476,
          "end_of_era_cutoff": 290.13916625976566
        }
      }
    }
  }
}